GoReturnsBear-0.9.0.1482008498.dist-info/DESCRIPTION.rst
GoReturnsBear-0.9.0.1482008498.dist-info/METADATA
GoReturnsBear-0.9.0.1482008498.dist-info/RECORD
GoReturnsBear-0.9.0.1482008498.dist-info/WHEEL
GoReturnsBear-0.9.0.1482008498.dist-info/entry_points.txt
GoReturnsBear-0.9.0.1482008498.dist-info/metadata.json
GoReturnsBear-0.9.0.1482008498.dist-info/top_level.txt
coalaGoReturnsBear/GoReturnsBear.py
coalaGoReturnsBear/__init__.py
