Metadata-Version: 2.0
Name: GoReturnsBear
Version: 0.9.0.1482008498
Summary: 'GoReturnsBear' bear for coala (http://coala.rtfd.org/)
Home-page: UNKNOWN
Author: UNKNOWN
Author-email: UNKNOWN
License: AGPL-3.0
Platform: any
Classifier: Development Status :: 4 - Beta
Classifier: Environment :: Console
Classifier: Environment :: Win32 (MS Windows)
Classifier: Intended Audience :: Science/Research
Classifier: Intended Audience :: Developers
Classifier: Programming Language :: Python :: Implementation :: CPython
Classifier: Programming Language :: Python :: 3.4
Classifier: Programming Language :: Python :: 3.5
Classifier: Programming Language :: Python :: 3 :: Only
Classifier: Topic :: Scientific/Engineering :: Information Analysis
Classifier: Topic :: Software Development :: Quality Assurance
Classifier: Topic :: Text Processing :: Linguistic
